Metadata-Version: 2.1
Name: procon
Version: 0.0.10
Summary: Conformance Checking on BPMN models
Home-page: https://github.com/require-gio/procon
Author: Giorgi Lomidze
Author-email: giorgi@giolom.com
License: GPL 3.0
Project-URL: Documentation, https://github.com/require-gio/procon
Project-URL: Source, https://github.com/require-gio/procon
Project-URL: Tracker, https://github.com/require-gio/procon/issues
Platform: UNKNOWN
Classifier: Programming Language :: Python :: 3
Classifier: License :: OSI Approved :: GNU General Public License v3 (GPLv3)
Classifier: Operating System :: OS Independent
Requires-Python: >=3.7
License-File: LICENSE
Requires-Dist: pm4py (==2.2.19.2)
Requires-Dist: pm4pycvxopt
Requires-Dist: psutil
